README.md
nosepipe.py
setup.cfg
setup.py
nosepipe.egg-info/PKG-INFO
nosepipe.egg-info/SOURCES.txt
nosepipe.egg-info/dependency_links.txt
nosepipe.egg-info/entry_points.txt
nosepipe.egg-info/requires.txt
nosepipe.egg-info/top_level.txt
nosepipe.egg-info/zip-safe