Metadata-Version: 1.1
Name: nosepipe
Version: 0.9
Summary: Plugin for the nose testing framework for running tests in a subprocess
Home-page: http://github.com/dmccombs/nosepipe/
Author: John J. Lee, Dan McCombs, Vadim Markovtsev
Author-email: dmccombs@dyn.com
License: BSD
Download-URL: http://pypi.python.org/pypi/nosepipe/
Platform: any
